MANIFEST.in
README.md
requirements.txt
setup.py
test-requirements.txt
pydiecalc/__init__.py
pydiecalc/client.py
pydiecalc.egg-info/PKG-INFO
pydiecalc.egg-info/SOURCES.txt
pydiecalc.egg-info/dependency_links.txt
pydiecalc.egg-info/entry_points.txt
pydiecalc.egg-info/requires.txt
pydiecalc.egg-info/top_level.txt
pydiecalc/tests/__init__.py
pydiecalc/tests/test_pydice.py