Metadata-Version: 1.0
Name: pydiecalc
Version: 0.1.1
Summary: python RPG Dice Parser and calculator
Home-page: https://github.com/roaet/pydiecalc
Author: Justin Hammond
Author-email: justin@roaet.com
License: UNKNOWN
Platform: UNKNOWN
